tenzir_mcp/__init__.py
tenzir_mcp/bootstrap.py
tenzir_mcp/docs.py
tenzir_mcp/logging_utils.py
tenzir_mcp/py.typed
tenzir_mcp/server.py
tenzir_mcp/data/__init__.py
tenzir_mcp/data/docs.db
tenzir_mcp/data/docs/.metadata.json
tenzir_mcp/data/docs/README.md
tenzir_mcp/data/docs/.claude/CLAUDE.md
tenzir_mcp/data/docs/.claude/rules/src-assets.md
tenzir_mcp/data/docs/.claude/rules/src-content-docs.md
tenzir_mcp/data/docs/.claude/rules/starlight-components.md
tenzir_mcp/data/docs/scripts/README.md
tenzir_mcp/data/docs/src/assets/css/README.md
tenzir_mcp/data/docs/src/content/docs/index.mdoc
tenzir_mcp/data/docs/src/content/docs/changelog/index.mdx
tenzir_mcp/data/docs/src/content/docs/explanations/configuration.mdoc
tenzir_mcp/data/docs/src/content/docs/explanations/enrichment.mdx
tenzir_mcp/data/docs/src/content/docs/explanations/faqs.mdx
tenzir_mcp/data/docs/src/content/docs/explanations/glossary.mdx
tenzir_mcp/data/docs/src/content/docs/explanations/index.mdoc
tenzir_mcp/data/docs/src/content/docs/explanations/packages.mdx
tenzir_mcp/data/docs/src/content/docs/explanations/architecture/index.mdx
tenzir_mcp/data/docs/src/content/docs/explanations/architecture/node/index.mdx
tenzir_mcp/data/docs/src/content/docs/explanations/architecture/pipeline/index.mdx
tenzir_mcp/data/docs/src/content/docs/explanations/architecture/platform/index.mdx
tenzir_mcp/data/docs/src/content/docs/explanations/language/expressions.mdx
tenzir_mcp/data/docs/src/content/docs/explanations/language/index.mdx
tenzir_mcp/data/docs/src/content/docs/explanations/language/programs.mdx
tenzir_mcp/data/docs/src/content/docs/explanations/language/statements.mdx
tenzir_mcp/data/docs/src/content/docs/explanations/language/types.mdx
tenzir_mcp/data/docs/src/content/docs/explanations/secrets/index.mdx
tenzir_mcp/data/docs/src/content/docs/guides/index.mdoc
tenzir_mcp/data/docs/src/content/docs/guides/account-creation/index.mdoc
tenzir_mcp/data/docs/src/content/docs/guides/ai-workbench/configure-your-agent.mdx
tenzir_mcp-0.4.5.dist-info/METADATA
tenzir_mcp-0.4.5.dist-info/WHEEL
tenzir_mcp-0.4.5.dist-info/entry_points.txt
tenzir_mcp-0.4.5.dist-info/licenses/LICENSE
tenzir_mcp-0.4.5.dist-info/RECORD
