Metadata-Version: 2.4
Name: tenzir-mcp
Version: 0.4.5
Summary: MCP server for Tenzir
Project-URL: Homepage, https://github.com/tenzir/mcp
Project-URL: Repository, https://github.com/tenzir/mcp
Project-URL: Documentation, https://docs.tenzir.com/reference/mcp-server
Project-URL: Source, https://github.com/tenzir/mcp
Project-URL: Bug Tracker, https://github.com/tenzir/mcp/issues
Author-email: Tenzir <engineering@tenzir.com>
Maintainer-email: Tenzir Engineering <engineering@tenzir.com>
License: Apache-2.0
License-File: LICENSE
Keywords: data-pipeline,mcp,model-context-protocol,ocsf,secdataops,secops,security,tenzir
Classifier: Development Status :: 4 - Beta
Classifier: Intended Audience :: Developers
Classifier: Intended Audience :: System Administrators
Classifier: License :: OSI Approved :: Apache Software License
Classifier: Operating System :: OS Independent
Classifier: Programming Language :: Python :: 3
Classifier: Programming Language :: Python :: 3.12
Classifier: Programming Language :: Python :: 3.13
Classifier: Topic :: Security
Classifier: Topic :: Software Development :: Libraries :: Python Modules
Classifier: Topic :: System :: Logging
Classifier: Topic :: System :: Monitoring
Classifier: Typing :: Typed
Requires-Python: >=3.12
Requires-Dist: fastmcp>=0.2.0
Requires-Dist: httpx>=0.25.0
Requires-Dist: pydantic>=2.0.0
Requires-Dist: python-dotenv>=1.0.0
Requires-Dist: tenzir-changelog>=0.8.1
Requires-Dist: tenzir-test>=0.12.0
